setup.py
trileans/__init__.py
trileans.egg-info/PKG-INFO
trileans.egg-info/SOURCES.txt
trileans.egg-info/dependency_links.txt
trileans.egg-info/top_level.txt