Metadata-Version: 1.1
Name: trileans
Version: 1.5.2
Summary: Trileans are three-valued objects.
Home-page: https://github.com/rittbys/Trileans
Author: rittbys
Author-email: UNKNOWN
License: MIT
Keywords: Trileans objects
Platform: UNKNOWN
Classifier: Development Status :: 5 - Production/Stable
Classifier: Programming Language :: Python :: 2
Classifier: Programming Language :: Python :: 2.7
Classifier: Programming Language :: Python :: 3
Classifier: Programming Language :: Python :: 3.4
